build_temp/CMakeCache.txt
build_temp/CoDeSEG
build_temp/Makefile
build_temp/cmake_install.cmake
build_temp/install_manifest.txt
build_temp/CMakeFiles/CMakeConfigureLog.yaml
build_temp/CMakeFiles/CMakeDirectoryInformation.cmake
build_temp/CMakeFiles/Makefile.cmake
build_temp/CMakeFiles/Makefile2
build_temp/CMakeFiles/TargetDirectories.txt
build_temp/CMakeFiles/cmake.check_cache
build_temp/CMakeFiles/progress.marks
build_temp/CMakeFiles/3.29.3/CMakeCCompiler.cmake
build_temp/CMakeFiles/3.29.3/CMakeCXXCompiler.cmake
build_temp/CMakeFiles/3.29.3/CMakeDetermineCompilerABI_C.bin
build_temp/CMakeFiles/3.29.3/CMakeDetermineCompilerABI_CXX.bin
build_temp/CMakeFiles/3.29.3/CMakeSystem.cmake
build_temp/CMakeFiles/3.29.3/CompilerIdC/CMakeCCompilerId.c
build_temp/CMakeFiles/3.29.3/CompilerIdC/a.out
build_temp/CMakeFiles/3.29.3/CompilerIdCXX/CMakeCXXCompilerId.cpp
build_temp/CMakeFiles/3.29.3/CompilerIdCXX/a.out
build_temp/CMakeFiles/CoDeSEG.dir/DependInfo.cmake
build_temp/CMakeFiles/CoDeSEG.dir/build.make
build_temp/CMakeFiles/CoDeSEG.dir/cmake_clean.cmake
build_temp/CMakeFiles/CoDeSEG.dir/compiler_depend.make
build_temp/CMakeFiles/CoDeSEG.dir/compiler_depend.ts
build_temp/CMakeFiles/CoDeSEG.dir/depend.make
build_temp/CMakeFiles/CoDeSEG.dir/flags.make
build_temp/CMakeFiles/CoDeSEG.dir/link.txt
build_temp/CMakeFiles/CoDeSEG.dir/progress.make
build_temp/CMakeFiles/CoDeSEG.dir/src/main.cpp.o
build_temp/CMakeFiles/CoDeSEG.dir/src/main.cpp.o.d
build_temp/CMakeFiles/CoDeSEG.dir/src/lib/CDS_Dynamic.cpp.o
build_temp/CMakeFiles/CoDeSEG.dir/src/lib/CDS_Dynamic.cpp.o.d
build_temp/CMakeFiles/CoDeSEG.dir/src/lib/CoDeSEG.cpp.o
build_temp/CMakeFiles/CoDeSEG.dir/src/lib/CoDeSEG.cpp.o.d
build_temp/CMakeFiles/CoDeSEG.dir/src/lib/DynamicArray.cpp.o
build_temp/CMakeFiles/CoDeSEG.dir/src/lib/DynamicArray.cpp.o.d
build_temp/CMakeFiles/CoDeSEG.dir/src/lib/Utility.cpp.o
build_temp/CMakeFiles/CoDeSEG.dir/src/lib/Utility.cpp.o.d
build_temp/bin/CoDeSEG
codeseg/__init__.py
codeseg/core.py
codeseg/utils.py
codeseg-1.0.0.dist-info/LICENSE
codeseg-1.0.0.dist-info/METADATA
codeseg-1.0.0.dist-info/WHEEL
codeseg-1.0.0.dist-info/top_level.txt
codeseg-1.0.0.dist-info/RECORD
