Metadata-Version: 2.1
Name: codeseg
Version: 1.0.0
Summary: CoDeSEG Community Detection Package
Home-page: https://github.com/Kust-lp/CoDeSEG
Author: Pu Li
Author-email: lipu2024626@gmail.com
Keywords: community detection,graph clustering
Classifier: Programming Language :: Python :: 3
Classifier: License :: OSI Approved :: MIT License
Classifier: Operating System :: OS Independent
Classifier: Intended Audience :: Science/Research
Classifier: Topic :: Scientific/Engineering :: Information Analysis
Requires-Python: >=3.8
License-File: LICENSE
